{"_table":{"_base":{"_airtable":{"requestTimeout":300000},"_id":"appahz1aZM65zk7IG"},"id":null,"name":"🍩 Oral Histories"},"id":"recILs8wwy0w0F2yL","_rawJson":{"id":"recILs8wwy0w0F2yL","fields":{"Source":["recBTGQQnXt3OdtaP","recNN99Of7Qlcf9zR"],"Notes":"Hotchkiss","Languages by ISO Code":["reclu8Eaxaa3kuv2X"],"Video Nation":["rec7DUYaTqWxRTABZ"],"Public (Youtube)":"To Upload","Date added":"2018-07-26","Speakers":["recxvCPnFPdG8Ph1G"],"Licenses":["rec7FnlQ3HE6p22Md"],"Video Territory":["recfnsLWdzFf6oHJw"],"Editing Status":"Unedited","Wikimedia Status":"Ineligible ","IDv2":"Andrey_20180726_rus","Languages Used":["Russian"],"italki call to action":["Get a free Russian lesson with italki: http://promos.italki.com/wikitongues_rus"],"italki active language":[true],".ID-languages":"rus","Languages per video":1,"Youtube URL":"No ID","Demographics":["137,000,000 in Russian Federation (2010 census). Population total all countries: 167,332,230."],"Language Continent":["reci7tcQABWNp7e4a","reci7tcQABWNp7e4a"],".speakerNames":"Andrey",".speakerNamesSanitized":"Andrey","Record Created At":"2018-07-26","Language Origin":["reczlA6AcGhGfxhcO","recifsmMRxsoj1H6V"],"YouTube License Statement":["The speaker(s) featured herein have not explicitly agreed to distribute this video for reuse. For inquiries on licensing this video, please contact hello@wikitongues.org."],".LanguagesNationOrigin":["reczlA6AcGhGfxhcO","recifsmMRxsoj1H6V"],"Geneaology":"\"[ Indo-European, Slavic, East ]\"",".wikimediaLicensingConflict":"no conflict"},"createdTime":"2018-07-26T22:13:06.000Z"},"fields":{"Source":["recBTGQQnXt3OdtaP","recNN99Of7Qlcf9zR"],"Notes":"Hotchkiss","Languages by ISO Code":["reclu8Eaxaa3kuv2X"],"Video Nation":["rec7DUYaTqWxRTABZ"],"Public (Youtube)":"To Upload","Date added":"2018-07-26","Speakers":["recxvCPnFPdG8Ph1G"],"Licenses":["rec7FnlQ3HE6p22Md"],"Video Territory":["recfnsLWdzFf6oHJw"],"Editing Status":"Unedited","Wikimedia Status":"Ineligible ","IDv2":"Andrey_20180726_rus","Languages Used":["Russian"],"italki call to action":["Get a free Russian lesson with italki: http://promos.italki.com/wikitongues_rus"],"italki active language":[true],".ID-languages":"rus","Languages per video":1,"Youtube URL":"No ID","Demographics":["137,000,000 in Russian Federation (2010 census). Population total all countries: 167,332,230."],"Language Continent":["reci7tcQABWNp7e4a","reci7tcQABWNp7e4a"],".speakerNames":"Andrey",".speakerNamesSanitized":"Andrey","Record Created At":"2018-07-26","Language Origin":["reczlA6AcGhGfxhcO","recifsmMRxsoj1H6V"],"YouTube License Statement":["The speaker(s) featured herein have not explicitly agreed to distribute this video for reuse. For inquiries on licensing this video, please contact hello@wikitongues.org."],".LanguagesNationOrigin":["reczlA6AcGhGfxhcO","recifsmMRxsoj1H6V"],"Geneaology":"\"[ Indo-European, Slavic, East ]\"",".wikimediaLicensingConflict":"no conflict"}}