{"_table":{"_base":{"_airtable":{"requestTimeout":300000},"_id":"appahz1aZM65zk7IG"},"id":null,"name":"🍩 Oral Histories"},"id":"rec0Z5lfWKLeSkLBJ","_rawJson":{"id":"rec0Z5lfWKLeSkLBJ","fields":{"Alternate Name":"New England French","Source":["recg1V3G2vkQIM7lZ"],"Languages by ISO Code":["rec87VCpIAAtXO9Ur"],"Video Nation":["rec7DUYaTqWxRTABZ"],"Public (Youtube)":"Public","Date added":"2015-04-07","Raw Thumbnail":[{"id":"attJ3lbfLIgpZxTtA","url":"https://dl.airtable.com/J6vWKVS2200j6pBYggq3_christian-fra-thumb-raw.png","filename":"christian-fra-thumb-raw.png","size":2454739,"type":"image/png","thumbnails":{"small":{"url":"https://dl.airtable.com/H5B22YZS2SEgaexbhJQD_christian-fra-thumb-raw.png","width":64,"height":36},"large":{"url":"https://dl.airtable.com/TXEO0eFlTkmpHOaOrrIP_christian-fra-thumb-raw.png","width":256,"height":144}}}],"Youtube Publish Schedule":"2015-04-07","Branded Thumbnail":[{"id":"attrV5eiLZJiyTykO","url":"https://dl.airtable.com/YRsGiXQBTu2icKcrTwxo_Christian_s1_M_20150407_fra.jpg","filename":"Christian_s1_M_20150407_fra.jpg","size":475707,"type":"image/jpeg","thumbnails":{"small":{"url":"https://dl.airtable.com/aSlPH1jTkCT3x1csLYzZ_small_Christian_s1_M_20150407_fra.jpg","width":64,"height":36},"large":{"url":"https://dl.airtable.com/BjMfp86xQk640MJooOO7_large_Christian_s1_M_20150407_fra.jpg","width":512,"height":512}}}],"italki video has link":true,"Youtube Banners Updated":true,"Youtube ID":"Z0Iv5hrJsho","Speakers":["recg1V3G2vkQIM7lZ"],"Top level genealogy per language":"Indo-European","Given language name":"New England French,,,,,","Licenses":["rec415gU0b0pymq5V"],"Editing Status":"Edited","Wikimedia Status":"Commons","Wiki Commons URL":"https://commons.wikimedia.org/wiki/File:WIKITONGUES-_Christian_speaking_New_England_French.webm","IDv2":"Christian_20150407_fra","Languages Used":["French"],"italki call to action":["Get a free French lesson with italki: http://promos.italki.com/wikitongues_fra"],"italki active language":[true],".ID-languages":"fra","Languages per video":1,"Youtube URL":"https://youtu.be/Z0Iv5hrJsho","Demographics":["60,000,000 in France (ELDIA 2012). Population total all countries: 74,980,460."],"Language Continent":["reci7tcQABWNp7e4a","reci7tcQABWNp7e4a","recrb3GtYD8nscmNi","reci7tcQABWNp7e4a","reci7tcQABWNp7e4a"],".speakerNames":"Christian",".speakerNamesSanitized":"Christian","Record Created At":"2015-03-19",".self?":1,"Language Origin":["recFiJey7GerKmdM6","recphEerSWeKK47dT","recFWUUkbXSrF3iq5","rec1r5sTcMBm9zLVN","recvbtv8Jg6o889rK"],"YouTube License Statement":["This video is licensed under a Creative Commons Attribution-NonCommercial 4.0 International license. To download a copy, please contact hello@wikitongues.org."],".LanguagesNationOrigin":["recFiJey7GerKmdM6","recphEerSWeKK47dT","recFWUUkbXSrF3iq5","rec1r5sTcMBm9zLVN","recvbtv8Jg6o889rK"],"Geneaology":"\"[ Indo-European, Italic, Romance, Italo-Western, Western, Gallo-Iberian, Gallo-Romance, Gallo-Rhaetian, Oïl, French ]\"","Sex":["Male"],".UserSubmitted(Presentation)":"User-submitted",".wikimediaLicensingConflict":"🔴conflict","Speaker Genders":["Male"]},"createdTime":"2015-03-19T20:37:26.000Z"},"fields":{"Alternate Name":"New England French","Source":["recg1V3G2vkQIM7lZ"],"Languages by ISO Code":["rec87VCpIAAtXO9Ur"],"Video Nation":["rec7DUYaTqWxRTABZ"],"Public (Youtube)":"Public","Date added":"2015-04-07","Raw Thumbnail":[{"id":"attJ3lbfLIgpZxTtA","url":"https://dl.airtable.com/J6vWKVS2200j6pBYggq3_christian-fra-thumb-raw.png","filename":"christian-fra-thumb-raw.png","size":2454739,"type":"image/png","thumbnails":{"small":{"url":"https://dl.airtable.com/H5B22YZS2SEgaexbhJQD_christian-fra-thumb-raw.png","width":64,"height":36},"large":{"url":"https://dl.airtable.com/TXEO0eFlTkmpHOaOrrIP_christian-fra-thumb-raw.png","width":256,"height":144}}}],"Youtube Publish Schedule":"2015-04-07","Branded Thumbnail":[{"id":"attrV5eiLZJiyTykO","url":"https://dl.airtable.com/YRsGiXQBTu2icKcrTwxo_Christian_s1_M_20150407_fra.jpg","filename":"Christian_s1_M_20150407_fra.jpg","size":475707,"type":"image/jpeg","thumbnails":{"small":{"url":"https://dl.airtable.com/aSlPH1jTkCT3x1csLYzZ_small_Christian_s1_M_20150407_fra.jpg","width":64,"height":36},"large":{"url":"https://dl.airtable.com/BjMfp86xQk640MJooOO7_large_Christian_s1_M_20150407_fra.jpg","width":512,"height":512}}}],"italki video has link":true,"Youtube Banners Updated":true,"Youtube ID":"Z0Iv5hrJsho","Speakers":["recg1V3G2vkQIM7lZ"],"Top level genealogy per language":"Indo-European","Given language name":"New England French,,,,,","Licenses":["rec415gU0b0pymq5V"],"Editing Status":"Edited","Wikimedia Status":"Commons","Wiki Commons URL":"https://commons.wikimedia.org/wiki/File:WIKITONGUES-_Christian_speaking_New_England_French.webm","IDv2":"Christian_20150407_fra","Languages Used":["French"],"italki call to action":["Get a free French lesson with italki: http://promos.italki.com/wikitongues_fra"],"italki active language":[true],".ID-languages":"fra","Languages per video":1,"Youtube URL":"https://youtu.be/Z0Iv5hrJsho","Demographics":["60,000,000 in France (ELDIA 2012). Population total all countries: 74,980,460."],"Language Continent":["reci7tcQABWNp7e4a","reci7tcQABWNp7e4a","recrb3GtYD8nscmNi","reci7tcQABWNp7e4a","reci7tcQABWNp7e4a"],".speakerNames":"Christian",".speakerNamesSanitized":"Christian","Record Created At":"2015-03-19",".self?":1,"Language Origin":["recFiJey7GerKmdM6","recphEerSWeKK47dT","recFWUUkbXSrF3iq5","rec1r5sTcMBm9zLVN","recvbtv8Jg6o889rK"],"YouTube License Statement":["This video is licensed under a Creative Commons Attribution-NonCommercial 4.0 International license. To download a copy, please contact hello@wikitongues.org."],".LanguagesNationOrigin":["recFiJey7GerKmdM6","recphEerSWeKK47dT","recFWUUkbXSrF3iq5","rec1r5sTcMBm9zLVN","recvbtv8Jg6o889rK"],"Geneaology":"\"[ Indo-European, Italic, Romance, Italo-Western, Western, Gallo-Iberian, Gallo-Romance, Gallo-Rhaetian, Oïl, French ]\"","Sex":["Male"],".UserSubmitted(Presentation)":"User-submitted",".wikimediaLicensingConflict":"🔴conflict","Speaker Genders":["Male"]}}