{"_table":{"_base":{"_airtable":{"requestTimeout":300000},"_id":"appahz1aZM65zk7IG"},"id":null,"name":"🍩 Oral Histories"},"id":"recQ78Y9qAsUrMgME","_rawJson":{"id":"recQ78Y9qAsUrMgME","fields":{"Source":["recjhBoGNppU34fe7"],"Notes":"Chatham","Languages by ISO Code":["recXkdIMV8vnE2e4m"],"Video Nation":["recs5BejB5FKc8QMi"],"Public (Youtube)":"Public","Date added":"2019-01-04","Publicity Clause":true,"Raw Thumbnail":[{"id":"attyKrdL0ykqMTQHU","url":"https://dl.airtable.com/.attachments/804134c830550b89a4f7d92c694021d9/52a4b4f3/ScreenShot2019-02-20at13.15.38.png","filename":"Screen Shot 2019-02-20 at 13.15.38.png","size":855117,"type":"image/png","thumbnails":{"small":{"url":"https://dl.airtable.com/.attachmentThumbnails/caa84fb2e0b6db410af6a66b55b9358b/df1b52c9","width":64,"height":36},"large":{"url":"https://dl.airtable.com/.attachmentThumbnails/1f26367e5722122f867dcb37ac63cf28/c9ea07e2","width":913,"height":512},"full":{"url":"https://dl.airtable.com/.attachmentThumbnails/638e6671f0fa025c55eaaeb3e2af0aad/57c6980d","width":1917,"height":1075}}}],"Youtube Publish Schedule":"2019-02-22","Branded Thumbnail":[{"id":"attPZCPZxTl0xkInZ","url":"https://dl.airtable.com/.attachments/92c3c49894bf05710cb93ccc183898ac/1beb146a/IainWilliam_20190104_bre.jpg","filename":"IainWilliam_20190104_bre.jpg","size":756700,"type":"image/jpeg","thumbnails":{"small":{"url":"https://dl.airtable.com/.attachmentThumbnails/74143e5a4f826089264dc059f5d7945b/f0962ba1","width":64,"height":36},"large":{"url":"https://dl.airtable.com/.attachmentThumbnails/2784112b270ef8dfa9be6886fc6c2fc6/2b0e3757","width":910,"height":512},"full":{"url":"https://dl.airtable.com/.attachmentThumbnails/1f510e34ae8b8bb0108832daf1bb5605/a2f365df","width":3000,"height":1688}}}],"Youtube ID":"6NCIYV3Q4d4","Speakers":["recjhBoGNppU34fe7"],"Video Description":"This video features Iain William Schofield speaking Breton in Ontario, Canada. Breton was spoken by around 206,000 people as of 2013, predominantly in France. As a Brythonic language, Bretton belongs to the Celtic branch of the Indo-European language family and is closely related to Cornish, another insular Celtic language. With proximity to French, Breton's phonology has been heavily influenced by the French language, distinguishing it from its insular relatives. Breton is the only living Celtic language that is not recognized as an official language by any government. Breton is classified by the UNESCO Atlas of the World's Languages In Danger as severely endangered, due to its decline from more than 1 million speakers in 1950 to roughly 200,000. However, the number of children learning Breton bilingually has risen sharply in the past decade, and several revitalization projects such as literary translations, bilingual dictionaries, Breton immersion education, and a Breton Wikipedia offer hope and vitality.","Licenses":["recz2qrZbzrYShYjh"],"Video Territory":["recPMWMqWU7mz8eyD"],"Editing Status":"Exported - WebM","Wikimedia Status":"Commons","Wiki Commons URL":"https://commons.wikimedia.org/wiki/File:WIKITONGUES-_Iain_William_speaking_Breton.webm","IDv2":"IainWilliam_20190104_bre","Languages Used":["Breton"],"italki active language":[null],".ID-languages":"bre","Languages per video":1,"Youtube URL":"https://youtu.be/6NCIYV3Q4d4","Demographics":["206,000 (2013 R. Milin), decreasing."],"Language Continent":["reci7tcQABWNp7e4a"],".speakerNames":"Iain William",".speakerNamesSanitized":"IainWilliam","Record Created At":"2019-01-09",".self?":1,"Language Origin":["recFiJey7GerKmdM6"],"YouTube License Statement":["This video is licensed under a Creative Commons Attribution-ShareAlike 4.0 International license. To download a copy, please contact hello@wikitongues.org."],".LanguagesNationOrigin":["recFiJey7GerKmdM6"],"Geneaology":"\"[ Indo-European, Celtic, Insular, Brythonic ]\"","Sex":["Male"],".UserSubmitted(Presentation)":"User-submitted",".wikimediaLicensingConflict":"no conflict","Speaker Genders":["Male"]},"createdTime":"2019-01-09T15:16:45.000Z"},"fields":{"Source":["recjhBoGNppU34fe7"],"Notes":"Chatham","Languages by ISO Code":["recXkdIMV8vnE2e4m"],"Video Nation":["recs5BejB5FKc8QMi"],"Public (Youtube)":"Public","Date added":"2019-01-04","Publicity Clause":true,"Raw Thumbnail":[{"id":"attyKrdL0ykqMTQHU","url":"https://dl.airtable.com/.attachments/804134c830550b89a4f7d92c694021d9/52a4b4f3/ScreenShot2019-02-20at13.15.38.png","filename":"Screen Shot 2019-02-20 at 13.15.38.png","size":855117,"type":"image/png","thumbnails":{"small":{"url":"https://dl.airtable.com/.attachmentThumbnails/caa84fb2e0b6db410af6a66b55b9358b/df1b52c9","width":64,"height":36},"large":{"url":"https://dl.airtable.com/.attachmentThumbnails/1f26367e5722122f867dcb37ac63cf28/c9ea07e2","width":913,"height":512},"full":{"url":"https://dl.airtable.com/.attachmentThumbnails/638e6671f0fa025c55eaaeb3e2af0aad/57c6980d","width":1917,"height":1075}}}],"Youtube Publish Schedule":"2019-02-22","Branded Thumbnail":[{"id":"attPZCPZxTl0xkInZ","url":"https://dl.airtable.com/.attachments/92c3c49894bf05710cb93ccc183898ac/1beb146a/IainWilliam_20190104_bre.jpg","filename":"IainWilliam_20190104_bre.jpg","size":756700,"type":"image/jpeg","thumbnails":{"small":{"url":"https://dl.airtable.com/.attachmentThumbnails/74143e5a4f826089264dc059f5d7945b/f0962ba1","width":64,"height":36},"large":{"url":"https://dl.airtable.com/.attachmentThumbnails/2784112b270ef8dfa9be6886fc6c2fc6/2b0e3757","width":910,"height":512},"full":{"url":"https://dl.airtable.com/.attachmentThumbnails/1f510e34ae8b8bb0108832daf1bb5605/a2f365df","width":3000,"height":1688}}}],"Youtube ID":"6NCIYV3Q4d4","Speakers":["recjhBoGNppU34fe7"],"Video Description":"This video features Iain William Schofield speaking Breton in Ontario, Canada. Breton was spoken by around 206,000 people as of 2013, predominantly in France. As a Brythonic language, Bretton belongs to the Celtic branch of the Indo-European language family and is closely related to Cornish, another insular Celtic language. With proximity to French, Breton's phonology has been heavily influenced by the French language, distinguishing it from its insular relatives. Breton is the only living Celtic language that is not recognized as an official language by any government. Breton is classified by the UNESCO Atlas of the World's Languages In Danger as severely endangered, due to its decline from more than 1 million speakers in 1950 to roughly 200,000. However, the number of children learning Breton bilingually has risen sharply in the past decade, and several revitalization projects such as literary translations, bilingual dictionaries, Breton immersion education, and a Breton Wikipedia offer hope and vitality.","Licenses":["recz2qrZbzrYShYjh"],"Video Territory":["recPMWMqWU7mz8eyD"],"Editing Status":"Exported - WebM","Wikimedia Status":"Commons","Wiki Commons URL":"https://commons.wikimedia.org/wiki/File:WIKITONGUES-_Iain_William_speaking_Breton.webm","IDv2":"IainWilliam_20190104_bre","Languages Used":["Breton"],"italki active language":[null],".ID-languages":"bre","Languages per video":1,"Youtube URL":"https://youtu.be/6NCIYV3Q4d4","Demographics":["206,000 (2013 R. Milin), decreasing."],"Language Continent":["reci7tcQABWNp7e4a"],".speakerNames":"Iain William",".speakerNamesSanitized":"IainWilliam","Record Created At":"2019-01-09",".self?":1,"Language Origin":["recFiJey7GerKmdM6"],"YouTube License Statement":["This video is licensed under a Creative Commons Attribution-ShareAlike 4.0 International license. To download a copy, please contact hello@wikitongues.org."],".LanguagesNationOrigin":["recFiJey7GerKmdM6"],"Geneaology":"\"[ Indo-European, Celtic, Insular, Brythonic ]\"","Sex":["Male"],".UserSubmitted(Presentation)":"User-submitted",".wikimediaLicensingConflict":"no conflict","Speaker Genders":["Male"]}}