{"_table":{"_base":{"_airtable":{"requestTimeout":300000},"_id":"appahz1aZM65zk7IG"},"id":null,"name":"🍩 Oral Histories"},"id":"recTjdGPkrNE5Y3W8","_rawJson":{"id":"recTjdGPkrNE5Y3W8","fields":{"Source":["recBTGQQnXt3OdtaP"],"Languages by ISO Code":["rec6Re4mpzSKKEWau"],"Video Nation":["recFiJey7GerKmdM6"],"Public (Youtube)":"Public","Date added":"2013-11-03","Raw Thumbnail":[{"id":"att4fJ3b7a9yviUTB","url":"https://dl.airtable.com/tpFN6hL8RU2e2KLBSAXX_sebastiano.png","filename":"sebastiano.png","size":1808074,"type":"image/png","thumbnails":{"small":{"url":"https://dl.airtable.com/6Rhcil8SpOyuzXnT2tnk_sebastiano.png","width":64,"height":36},"large":{"url":"https://dl.airtable.com/QlI6fu3RfOlsrZ6LzTh6_sebastiano.png","width":256,"height":145}}}],"Youtube Publish Schedule":"2013-11-03","Branded Thumbnail":[{"id":"attiT1gAmBk2T1Jtu","url":"https://dl.airtable.com/6tkeC3aeRR6ACViTB9F7_Sebastiano_s1_M_20131103_ita.jpg","filename":"Sebastiano_s1_M_20131103_ita.jpg","size":485984,"type":"image/jpeg","thumbnails":{"small":{"url":"https://dl.airtable.com/dMUfoUCnSPKCYGerV1DU_small_Sebastiano_s1_M_20131103_ita.jpg","width":64,"height":36},"large":{"url":"https://dl.airtable.com/6d8iqOpmT268HgVrLPBj_large_Sebastiano_s1_M_20131103_ita.jpg","width":512,"height":512}}}],"italki video has link":true,"Youtube Banners Updated":true,"Youtube ID":"jjiXgRO8qDw","Speakers":["recSEASEGDuicnH2C"],"Top level genealogy per language":"Indo-European","Given language name":"Italian,,,,,","Licenses":["rec7FnlQ3HE6p22Md"],"Captions by ISO Code":["rec6Re4mpzSKKEWau","recfoPadefGwwexHT","recJYjm4GOIV6thhs"],"Caption File Link":"https://www.dropbox.com/sh/ljwrz6undok61zx/AACrqHWgKRD4XINsfcdvVL1Ma?dl=0","Editing Status":"Edited","Wikimedia Status":"Ineligible ","IDv2":"Sebastiano_20131103_ita","Languages Used":["Italian"],"italki call to action":["Get a free Italian lesson with italki: http://promos.italki.com/wikitongues_ita"],"italki active language":[true],".ID-languages":"ita","Languages per video":1,"Youtube URL":"https://youtu.be/jjiXgRO8qDw","Demographics":["57,700,000 in Italy (ELDIA 2012). Population total all countries: 63,655,047."],"Language Continent":["reci7tcQABWNp7e4a","reci7tcQABWNp7e4a"],".speakerNames":"Sebastiano",".speakerNamesSanitized":"Sebastiano","Record Created At":"2014-12-22","Language Origin":["recFCahqH3mHr4HP5","rec1r5sTcMBm9zLVN"],"YouTube License Statement":["The speaker(s) featured herein have not explicitly agreed to distribute this video for reuse. For inquiries on licensing this video, please contact hello@wikitongues.org."],".LanguagesNationOrigin":["recFCahqH3mHr4HP5","rec1r5sTcMBm9zLVN"],"Geneaology":"\"[ Indo-European, Italic, Romance, Italo-Western, Italo-Dalmatian ]\"","Sex":["Male"],".wikimediaLicensingConflict":"no conflict","Speaker Genders":["Male"]},"createdTime":"2014-12-22T19:46:42.000Z"},"fields":{"Source":["recBTGQQnXt3OdtaP"],"Languages by ISO Code":["rec6Re4mpzSKKEWau"],"Video Nation":["recFiJey7GerKmdM6"],"Public (Youtube)":"Public","Date added":"2013-11-03","Raw Thumbnail":[{"id":"att4fJ3b7a9yviUTB","url":"https://dl.airtable.com/tpFN6hL8RU2e2KLBSAXX_sebastiano.png","filename":"sebastiano.png","size":1808074,"type":"image/png","thumbnails":{"small":{"url":"https://dl.airtable.com/6Rhcil8SpOyuzXnT2tnk_sebastiano.png","width":64,"height":36},"large":{"url":"https://dl.airtable.com/QlI6fu3RfOlsrZ6LzTh6_sebastiano.png","width":256,"height":145}}}],"Youtube Publish Schedule":"2013-11-03","Branded Thumbnail":[{"id":"attiT1gAmBk2T1Jtu","url":"https://dl.airtable.com/6tkeC3aeRR6ACViTB9F7_Sebastiano_s1_M_20131103_ita.jpg","filename":"Sebastiano_s1_M_20131103_ita.jpg","size":485984,"type":"image/jpeg","thumbnails":{"small":{"url":"https://dl.airtable.com/dMUfoUCnSPKCYGerV1DU_small_Sebastiano_s1_M_20131103_ita.jpg","width":64,"height":36},"large":{"url":"https://dl.airtable.com/6d8iqOpmT268HgVrLPBj_large_Sebastiano_s1_M_20131103_ita.jpg","width":512,"height":512}}}],"italki video has link":true,"Youtube Banners Updated":true,"Youtube ID":"jjiXgRO8qDw","Speakers":["recSEASEGDuicnH2C"],"Top level genealogy per language":"Indo-European","Given language name":"Italian,,,,,","Licenses":["rec7FnlQ3HE6p22Md"],"Captions by ISO Code":["rec6Re4mpzSKKEWau","recfoPadefGwwexHT","recJYjm4GOIV6thhs"],"Caption File Link":"https://www.dropbox.com/sh/ljwrz6undok61zx/AACrqHWgKRD4XINsfcdvVL1Ma?dl=0","Editing Status":"Edited","Wikimedia Status":"Ineligible ","IDv2":"Sebastiano_20131103_ita","Languages Used":["Italian"],"italki call to action":["Get a free Italian lesson with italki: http://promos.italki.com/wikitongues_ita"],"italki active language":[true],".ID-languages":"ita","Languages per video":1,"Youtube URL":"https://youtu.be/jjiXgRO8qDw","Demographics":["57,700,000 in Italy (ELDIA 2012). Population total all countries: 63,655,047."],"Language Continent":["reci7tcQABWNp7e4a","reci7tcQABWNp7e4a"],".speakerNames":"Sebastiano",".speakerNamesSanitized":"Sebastiano","Record Created At":"2014-12-22","Language Origin":["recFCahqH3mHr4HP5","rec1r5sTcMBm9zLVN"],"YouTube License Statement":["The speaker(s) featured herein have not explicitly agreed to distribute this video for reuse. For inquiries on licensing this video, please contact hello@wikitongues.org."],".LanguagesNationOrigin":["recFCahqH3mHr4HP5","rec1r5sTcMBm9zLVN"],"Geneaology":"\"[ Indo-European, Italic, Romance, Italo-Western, Italo-Dalmatian ]\"","Sex":["Male"],".wikimediaLicensingConflict":"no conflict","Speaker Genders":["Male"]}}